pymaid/__init__.py
pymaid/cache.py
pymaid/client.py
pymaid/cluster.py
pymaid/config.py
pymaid/connectivity.py
pymaid/core.py
pymaid/cytoscape.py
pymaid/morpho.py
pymaid/neuron_label.py
pymaid/stack.py
pymaid/tiles.py
pymaid/upload.py
pymaid/user_stats.py
pymaid/utils.py
pymaid/fetch/__init__.py
pymaid/fetch/annotations.py
pymaid/fetch/landmarks.py
pymaid/fetch/skeletons.py
pymaid/fetch/stack.py
python_catmaid-2.4.1.dist-info/LICENSE
python_catmaid-2.4.1.dist-info/METADATA
python_catmaid-2.4.1.dist-info/WHEEL
python_catmaid-2.4.1.dist-info/top_level.txt
python_catmaid-2.4.1.dist-info/RECORD
