Metadata-Version: 2.1
Name: python-catmaid
Version: 2.4.1
Summary: Python interface to CATMAID servers
Home-page: https://github.com/navis-org/pymaid
Author: Philipp Schlegel
Author-email: pms70@cam.ac.uk
License: GNU GPL V3
Project-URL: Documentation, http://pymaid.readthedocs.io
Project-URL: Source, https://github.com/navis-org/pymaid
Project-URL: Changelog, https://pymaid.readthedocs.io/en/latest/source/whats_new.html
Keywords: CATMAID interface neuron navis
Classifier: Development Status :: 5 - Production/Stable
Classifier: Intended Audience :: Science/Research
Classifier: Topic :: Scientific/Engineering :: Bio-Informatics
Classifier: License :: OSI Approved :: GNU General Public License v3 or later (GPLv3+)
Classifier: Programming Language :: Python :: 3
Classifier: Programming Language :: Python :: 3.9
Classifier: Programming Language :: Python :: 3.10
Classifier: Programming Language :: Python :: 3.11
Requires-Python: >=3.9
License-File: LICENSE
Requires-Dist: navis>=1.0.0
Requires-Dist: numpy>=1.16.3
Requires-Dist: networkx>=2.4
Requires-Dist: pandas>=1.0
Requires-Dist: requests-futures>=0.9.9
Requires-Dist: requests>=2.21.0
Requires-Dist: setuptools>=41.0.1
Requires-Dist: scipy>=1.3.0
Requires-Dist: six>=1.11.0
Requires-Dist: tqdm>=4.50.0
Requires-Dist: psutil>=5.4.3
Provides-Extra: all
Requires-Dist: xarray[parallel]; extra == "all"
Requires-Dist: imageio; extra == "all"
Requires-Dist: ujson~=1.35; extra == "all"
Requires-Dist: zarr; extra == "all"
Requires-Dist: fsspec[http]; extra == "all"
Provides-Extra: extras
Requires-Dist: ujson~=1.35; extra == "extras"
Provides-Extra: stack
Requires-Dist: zarr; extra == "stack"
Requires-Dist: fsspec[http]; extra == "stack"
Requires-Dist: xarray[parallel]; extra == "stack"
Requires-Dist: imageio; extra == "stack"
